[
  {
    "name": "NOC Home",
    "url": "http://noc.mytechinfra.com",
    "ip": "142.132.149.97",
    "status": "UP",
    "responseTime": 429.5,
    "timestamp": "2026-04-26T15:55:34.993391Z"
  },
  {
    "name": "Fokas Mail",
    "url": "https://mail.fokasmulia.com.my",
    "ip": "103.240.177.89",
    "status": "UP",
    "responseTime": 771.57,
    "timestamp": "2026-04-26T15:55:34.993391Z"
  },
  {
    "name": "TechInfra Webmail",
    "url": "https://webmail.mytechinfra.com",
    "ip": "103.240.177.88",
    "status": "UP",
    "responseTime": 975.2,
    "timestamp": "2026-04-26T15:55:34.993391Z"
  },
  {
    "name": "MyEG Webmail",
    "url": "https://webmail.myeg.com.my",
    "ip": "103.240.177.90",
    "status": "UP",
    "responseTime": 804.77,
    "timestamp": "2026-04-26T15:55:34.993391Z"
  },
  {
    "name": "WhatsApp Web",
    "url": "https://web.whatsapp.com",
    "ip": "163.70.132.60",
    "status": "UP",
    "responseTime": 918.0,
    "timestamp": "2026-04-26T15:55:34.993391Z"
  },
  {
    "name": "Agent Login",
    "url": "https://login2agent.pacific-orient.com",
    "ip": "203.10.20.120",
    "status": "UP",
    "responseTime": 1927.06,
    "timestamp": "2026-04-26T15:55:34.993391Z"
  },
  {
    "name": "MyCarInfo",
    "url": "http://www.mycarinfo.com.my",
    "ip": "203.115.229.88",
    "status": "UP",
    "responseTime": 1789.48,
    "timestamp": "2026-04-26T15:55:34.993391Z"
  }
]