[
  {
    "name": "NOC Home",
    "url": "http://noc.mytechinfra.com",
    "ip": "142.132.149.97",
    "status": "UP",
    "responseTime": 639.02,
    "timestamp": "2026-05-11T06:26:00.213566Z"
  },
  {
    "name": "Fokas Mail",
    "url": "https://mail.fokasmulia.com.my",
    "ip": "103.240.177.89",
    "status": "UP",
    "responseTime": 621.2,
    "timestamp": "2026-05-11T06:26:00.213566Z"
  },
  {
    "name": "TechInfra Webmail",
    "url": "https://webmail.mytechinfra.com",
    "ip": "103.240.177.88",
    "status": "UP",
    "responseTime": 1024.17,
    "timestamp": "2026-05-11T06:26:00.213566Z"
  },
  {
    "name": "MyEG Webmail",
    "url": "https://webmail.myeg.com.my",
    "ip": "103.240.177.90",
    "status": "UP",
    "responseTime": 642.82,
    "timestamp": "2026-05-11T06:26:00.213566Z"
  },
  {
    "name": "WhatsApp Web",
    "url": "https://web.whatsapp.com",
    "ip": "163.70.132.60",
    "status": "UP",
    "responseTime": 372.57,
    "timestamp": "2026-05-11T06:26:00.213566Z"
  },
  {
    "name": "Agent Login",
    "url": "https://login2agent.pacific-orient.com",
    "ip": "203.10.20.120",
    "status": "UP",
    "responseTime": 1946.64,
    "timestamp": "2026-05-11T06:26:00.213566Z"
  },
  {
    "name": "MyCarInfo",
    "url": "http://www.mycarinfo.com.my",
    "ip": "203.115.229.88",
    "status": "UP",
    "responseTime": 973.64,
    "timestamp": "2026-05-11T06:26:00.213566Z"
  }
]